{
  "alkeet": [
    {
    "name": "alkeet vaihtuvilla pareilla",
    "teacher": "Kimmo Luukkonen",
    "start": "17:00",
    "end": "18:30"
    }
  ],
  "alkeetOma": [
    {
    "name": "alkeet oman parin kanssa",
    "teacher": "Marianne Kraus",
    "start": "18:30",
    "end": "20:00"
    }
  ],
  "alkeisjatko": [
    {
    "name": "alkeisjatko",
    "teacher": "Kimmo Luukkonen",
    "start": "17:00",
    "end": "18:30"
    }
  ],
  "jatko": [
    {
    "name": "jatkokurssi",
    "teacher": "Marianne Kraus",
    "start": "18:30",
    "end": "20:00"
    }
  ]
}
